AUTHORS
CHANGELOG.rst
LICENSE
MANIFEST.in
README.rst
setup.cfg
setup.py
addonpayments/__init__.py
addonpayments/exceptions.py
addonpayments/logger.py
addonpayments/mixins.py
addonpayments/responses.py
addonpayments/utils.py
addonpayments/validators.py
addonpayments/api/__init__.py
addonpayments/api/client.py
addonpayments/api/elements.py
addonpayments/api/mixins.py
addonpayments/api/utils.py
addonpayments/api/validators.py
addonpayments/api/card_storage/__init__.py
addonpayments/api/card_storage/requests.py
addonpayments/api/common/__init__.py
addonpayments/api/common/requests.py
addonpayments/api/common/responses.py
addonpayments/api/dcc/__init__.py
addonpayments/api/dcc/requests.py
addonpayments/api/payment/__init__.py
addonpayments/api/payment/requests.py
addonpayments/api/three_ds/__init__.py
addonpayments/api/three_ds/requests.py
addonpayments/api/three_ds/validators.py
addonpayments/api/transaction_management/__init__.py
addonpayments/api/transaction_management/requests.py
addonpayments/api/transaction_management/validators.py
addonpayments/hpp/__init__.py
addonpayments/hpp/hpp.py
addonpayments/hpp/utils.py
addonpayments/hpp/validators.py
addonpayments/hpp/card_storage/__init__.py
addonpayments/hpp/card_storage/requests.py
addonpayments/hpp/card_storage/validators.py
addonpayments/hpp/common/__init__.py
addonpayments/hpp/common/requests.py
addonpayments/hpp/common/responses.py
addonpayments/hpp/payment/__init__.py
addonpayments/hpp/payment/requests.py
addonpayments_sdk_python.egg-info/PKG-INFO
addonpayments_sdk_python.egg-info/SOURCES.txt
addonpayments_sdk_python.egg-info/dependency_links.txt
addonpayments_sdk_python.egg-info/not-zip-safe
addonpayments_sdk_python.egg-info/requires.txt
addonpayments_sdk_python.egg-info/top_level.txt
tests/__init__.py
tests/conftest.py
tests/hpp/__init__.py
tests/hpp/utils.py