Metadata-Version: 1.1
Name: addonpayments-sdk-python
Version: 0.2.9
Summary: A SDK Addonpayments implemented with Python.
Home-page: https://github.com/ComerciaGP/addonpayments-Python-SDK
Author: Marc Galofré
Author-email: mgalofre@apsl.com
License: BSD
Platform: UNKNOWN
Classifier: Environment :: Web Environment
Classifier: Intended Audience :: Developers
Classifier: Programming Language :: Python
Classifier: Programming Language :: Python :: 2
Classifier: Programming Language :: Python :: 2.7
Classifier: Programming Language :: Python :: 3
Classifier: Programming Language :: Python :: 3.5
Classifier: Operating System :: OS Independent
Classifier: Topic :: Software Development
